[
  {
    "type": "movie",
    "title": "Inception",
    "release_year": 2010,
    "date": "2010-01-01T00:00:00.000Z",
    "review": {
      "rating": 4
    },
    "genres": [
      "Action",
      "Adventure",
      "Sci-Fi"
    ],
    "director": [
      "Christopher Nolan"
    ]
  },
  {
    "type": "movie",
    "title": "Shutter Island",
    "release_year": 2010,
    "date": "2010-01-01T00:00:00.000Z",
    "review": {
      "rating": 5
    },
    "genres": [
      "Mystery",
      "Thriller"
    ],
    "director": [
      "Martin Scorsese"
    ]
  },
  {
    "type": "movie",
    "title": "Kick-Ass",
    "release_year": 2010,
    "date": "2010-01-01T00:00:00.000Z",
    "review": {
      "rating": 5
    },
    "genres": [
      "Action",
      "Comedy",
      "Crime"
    ],
    "director": [
      "Matthew Vaughn"
    ]
  },
  {
    "type": "movie",
    "title": "The Social Network",
    "release_year": 2010,
    "date": "2010-01-01T00:00:00.000Z",
    "review": {
      "rating": 4
    },
    "genres": [
      "Biography",
      "Drama"
    ],
    "director": [
      "David Fincher"
    ]
  },
  {
    "type": "movie",
    "title": "Iron Man 2",
    "release_year": 2010,
    "date": "2010-01-01T00:00:00.000Z",
    "review": {
      "rating": 4
    },
    "genres": [
      "Action",
      "Adventure",
      "Sci-Fi"
    ],
    "director": [
      "Jon Favreau"
    ]
  },
  {
    "type": "movie",
    "title": "The Expendables",
    "release_year": 2010,
    "date": "2010-01-01T00:00:00.000Z",
    "review": {
      "rating": 3
    },
    "genres": [
      "Action",
      "Adventure",
      "Thriller"
    ],
    "director": [
      "Sylvester Stallone"
    ]
  },
  {
    "type": "movie",
    "title": "Prince of Persia: The Sands of Time",
    "release_year": 2010,
    "date": "2010-01-01T00:00:00.000Z",
    "review": {
      "rating": 4
    },
    "genres": [
      "Action",
      "Adventure",
      "Fantasy"
    ],
    "director": [
      "Mike Newell"
    ]
  },
  {
    "type": "movie",
    "title": "127 Hours",
    "release_year": 2010,
    "date": "2010-01-01T00:00:00.000Z",
    "review": {
      "rating": 4
    },
    "genres": [
      "Biography",
      "Drama"
    ],
    "director": [
      "Danny Boyle"
    ]
  },
  {
    "type": "movie",
    "title": "Salt",
    "release_year": 2010,
    "date": "2010-01-01T00:00:00.000Z",
    "review": {
      "rating": 3
    },
    "genres": [
      "Action",
      "Thriller"
    ],
    "director": [
      "Phillip Noyce"
    ]
  },
  {
    "type": "movie",
    "title": "Due Date",
    "release_year": 2010,
    "date": "2010-01-01T00:00:00.000Z",
    "review": {
      "rating": 3
    },
    "genres": [
      "Comedy",
      "Drama"
    ],
    "director": [
      "Todd Phillips"
    ]
  },
  {
    "type": "movie",
    "title": "Repo Men",
    "release_year": 2010,
    "date": "2010-01-01T00:00:00.000Z",
    "review": {
      "rating": 2
    },
    "genres": [
      "Action",
      "Sci-Fi",
      "Thriller"
    ],
    "director": [
      "Miguel Sapochnik"
    ]
  },
  {
    "type": "movie",
    "title": "Drive",
    "release_year": 2011,
    "date": "2011-01-01T00:00:00.000Z",
    "review": {
      "rating": 5
    },
    "genres": [
      "Action",
      "Drama"
    ],
    "director": [
      "Nicolas Winding Refn"
    ]
  },
  {
    "type": "movie",
    "title": "Captain America: The First Avenger",
    "release_year": 2011,
    "date": "2011-01-01T00:00:00.000Z",
    "review": {
      "rating": 3
    },
    "genres": [
      "Action",
      "Adventure",
      "Sci-Fi"
    ],
    "director": [
      "Joe Johnston"
    ]
  },
  {
    "type": "movie",
    "title": "Thor",
    "release_year": 2011,
    "date": "2011-01-01T00:00:00.000Z",
    "review": {
      "rating": 3
    },
    "genres": [
      "Action",
      "Adventure",
      "Fantasy"
    ],
    "director": [
      "Kenneth Branagh"
    ]
  },
  {
    "type": "movie",
    "title": "X-Men: First Class",
    "release_year": 2011,
    "date": "2011-01-01T00:00:00.000Z",
    "review": {
      "rating": 4
    },
    "genres": [
      "Action",
      "Adventure",
      "Sci-Fi"
    ],
    "director": [
      "Matthew Vaughn"
    ]
  },
  {
    "type": "movie",
    "title": "Limitless",
    "release_year": 2011,
    "date": "2011-01-01T00:00:00.000Z",
    "review": {
      "rating": 4
    },
    "genres": [
      "Sci-Fi",
      "Thriller"
    ],
    "director": [
      "Neil Burger"
    ]
  },
  {
    "type": "movie",
    "title": "Horrible Bosses",
    "release_year": 2011,
    "date": "2011-01-01T00:00:00.000Z",
    "review": {
      "rating": 4
    },
    "genres": [
      "Comedy",
      "Crime"
    ],
    "director": [
      "Seth Gordon"
    ]
  },
  {
    "type": "movie",
    "title": "The Hangover Part II",
    "release_year": 2011,
    "date": "2011-01-01T00:00:00.000Z",
    "review": {
      "rating": 4
    },
    "genres": [
      "Comedy"
    ],
    "director": [
      "Todd Phillips"
    ]
  },
  {
    "type": "movie",
    "title": "Fast Five",
    "release_year": 2011,
    "date": "2011-01-01T00:00:00.000Z",
    "review": {
      "rating": 3
    },
    "genres": [
      "Action",
      "Crime",
      "Thriller"
    ],
    "director": [
      "Justin Lin"
    ]
  },
  {
    "type": "movie",
    "title": "Real Steel",
    "release_year": 2011,
    "date": "2011-01-01T00:00:00.000Z",
    "review": {
      "rating": 2
    },
    "genres": [
      "Action",
      "Drama",
      "Sci-Fi"
    ],
    "director": [
      "Shawn Levy"
    ]
  },
  {
    "type": "movie",
    "title": "Django Unchained",
    "release_year": 2012,
    "date": "2012-01-01T00:00:00.000Z",
    "review": {
      "rating": 5
    },
    "genres": [
      "Drama",
      "Western"
    ],
    "director": [
      "Quentin Tarantino"
    ]
  },
  {
    "type": "movie",
    "title": "The Dark Knight Rises",
    "release_year": 2012,
    "date": "2012-01-01T00:00:00.000Z",
    "review": {
      "rating": 5
    },
    "genres": [
      "Action",
      "Drama"
    ],
    "director": [
      "Christopher Nolan"
    ]
  },
  {
    "type": "movie",
    "title": "The Hobbit: An Unexpected Journey",
    "release_year": 2012,
    "date": "2012-01-01T00:00:00.000Z",
    "review": {
      "rating": 2
    },
    "genres": [
      "Adventure",
      "Fantasy"
    ],
    "director": [
      "Peter Jackson"
    ]
  },
  {
    "type": "movie",
    "title": "The Avengers",
    "release_year": 2012,
    "date": "2012-01-01T00:00:00.000Z",
    "review": {
      "rating": 4
    },
    "genres": [
      "Action",
      "Adventure",
      "Sci-Fi"
    ],
    "director": [
      "Joss Whedon"
    ]
  },
  {
    "type": "movie",
    "title": "21 Jump Street",
    "release_year": 2012,
    "date": "2012-01-01T00:00:00.000Z",
    "review": {
      "rating": 4
    },
    "genres": [
      "Action",
      "Comedy",
      "Crime"
    ],
    "director": [
      "Phil Lord",
      "Christopher Miller"
    ]
  },
  {
    "type": "movie",
    "title": "Skyfall",
    "release_year": 2012,
    "date": "2012-01-01T00:00:00.000Z",
    "review": {
      "rating": 4
    },
    "genres": [
      "Action",
      "Adventure",
      "Thriller"
    ],
    "director": [
      "Sam Mendes"
    ]
  },
  {
    "type": "movie",
    "title": "Prometheus",
    "release_year": 2012,
    "date": "2012-01-01T00:00:00.000Z",
    "review": {
      "rating": 4
    },
    "genres": [
      "Adventure",
      "Mystery",
      "Sci-Fi"
    ],
    "director": [
      "Ridley Scott"
    ]
  },
  {
    "type": "movie",
    "title": "Looper",
    "release_year": 2012,
    "date": "2012-01-01T00:00:00.000Z",
    "review": {
      "rating": 4
    },
    "genres": [
      "Action",
      "Drama",
      "Sci-Fi"
    ],
    "director": [
      "Rian Johnson"
    ]
  },
  {
    "type": "movie",
    "title": "The Amazing Spider-Man",
    "release_year": 2012,
    "date": "2012-01-01T00:00:00.000Z",
    "review": {
      "rating": 4
    },
    "genres": [
      "Action",
      "Adventure",
      "Sci-Fi"
    ],
    "director": [
      "Marc Webb"
    ]
  },
  {
    "type": "movie",
    "title": "Ted",
    "release_year": 2012,
    "date": "2012-01-01T00:00:00.000Z",
    "review": {
      "rating": 3
    },
    "genres": [
      "Comedy"
    ],
    "director": [
      "Seth MacFarlane"
    ]
  },
  {
    "type": "movie",
    "title": "The Bourne Legacy",
    "release_year": 2012,
    "date": "2012-01-01T00:00:00.000Z",
    "review": {
      "rating": 4
    },
    "genres": [
      "Action",
      "Adventure",
      "Thriller"
    ],
    "director": [
      "Tony Gilroy"
    ]
  },
  {
    "type": "movie",
    "title": "The Dictator",
    "release_year": 2012,
    "date": "2012-01-01T00:00:00.000Z",
    "review": {
      "rating": 4
    },
    "genres": [
      "Comedy"
    ],
    "director": [
      "Larry Charles"
    ]
  },
  {
    "type": "movie",
    "title": "That's My Boy",
    "release_year": 2012,
    "date": "2012-01-01T00:00:00.000Z",
    "review": {
      "rating": 4
    },
    "genres": [
      "Comedy"
    ],
    "director": [
      "Sean Anders"
    ]
  },
  {
    "type": "movie",
    "title": "Battleship",
    "release_year": 2012,
    "date": "2012-01-01T00:00:00.000Z",
    "review": {
      "rating": 1
    },
    "genres": [
      "Action",
      "Adventure",
      "Sci-Fi"
    ],
    "director": [
      "Peter Berg"
    ]
  },
  {
    "type": "movie",
    "title": "Project-X",
    "release_year": 2010,
    "date": "2012-01-01T00:00:00.000Z",
    "review": {
      "rating": 4
    },
    "genres": [
      "Horror",
      "Sci-Fi"
    ],
    "director": [
      "Jose F. Sanchez"
    ]
  },
  {
    "type": "movie",
    "title": "Brave",
    "release_year": 2012,
    "date": "2012-01-01T00:00:00.000Z",
    "review": {
      "rating": 4
    },
    "genres": [
      "Animation",
      "Adventure",
      "Comedy"
    ],
    "director": [
      "Mark Andrews",
      "Brenda Chapman",
      "Steve Purcell"
    ]
  },
  {
    "type": "movie",
    "title": "Chronicle",
    "release_year": 2012,
    "date": "2012-01-01T00:00:00.000Z",
    "review": {
      "rating": 4
    },
    "genres": [
      "Action",
      "Drama",
      "Sci-Fi"
    ],
    "director": [
      "Josh Trank"
    ]
  },
  {
    "type": "movie",
    "title": "American Reunion",
    "release_year": 2012,
    "date": "2012-01-01T00:00:00.000Z",
    "review": {
      "rating": 3
    },
    "genres": [
      "Comedy"
    ],
    "director": [
      "Jon Hurwitz",
      "Hayden Schlossberg"
    ]
  },
  {
    "type": "movie",
    "title": "Taken 2",
    "release_year": 2012,
    "date": "2012-01-01T00:00:00.000Z",
    "review": {
      "rating": 1
    },
    "genres": [
      "Action",
      "Crime",
      "Thriller"
    ],
    "director": [
      "Olivier Megaton"
    ]
  },
  {
    "type": "movie",
    "title": "Safe",
    "release_year": 2012,
    "date": "2012-01-01T00:00:00.000Z",
    "review": {
      "rating": 3
    },
    "genres": [
      "Action",
      "Crime",
      "Thriller"
    ],
    "director": [
      "Boaz Yakin"
    ]
  },
  {
    "type": "movie",
    "title": "Kon-Tiki",
    "release_year": 2012,
    "date": "2012-01-01T00:00:00.000Z",
    "review": {
      "rating": 4
    },
    "genres": [
      "Action",
      "Adventure",
      "Biography"
    ],
    "director": [
      "Joachim Rønning",
      "Espen Sandberg"
    ]
  },
  {
    "type": "movie",
    "title": "The Wolf of Wall Street",
    "release_year": 2013,
    "date": "2013-01-01T00:00:00.000Z",
    "review": {
      "rating": 5
    },
    "genres": [
      "Biography",
      "Comedy",
      "Crime"
    ],
    "director": [
      "Martin Scorsese"
    ]
  },
  {
    "type": "movie",
    "title": "Her",
    "release_year": 2013,
    "date": "2013-01-01T00:00:00.000Z",
    "review": {
      "rating": 5
    },
    "genres": [
      "Drama",
      "Romance",
      "Sci-Fi"
    ],
    "director": [
      "Spike Jonze"
    ]
  },
  {
    "type": "movie",
    "title": "Man of Steel",
    "release_year": 2013,
    "date": "2013-01-01T00:00:00.000Z",
    "review": {
      "rating": 4
    },
    "genres": [
      "Action",
      "Adventure",
      "Sci-Fi"
    ],
    "director": [
      "Zack Snyder"
    ]
  },
  {
    "type": "movie",
    "title": "Oblivion",
    "release_year": 2013,
    "date": "2013-01-01T00:00:00.000Z",
    "review": {
      "rating": 3
    },
    "genres": [
      "Action",
      "Adventure",
      "Sci-Fi"
    ],
    "director": [
      "Joseph Kosinski"
    ]
  },
  {
    "type": "movie",
    "title": "We're the Millers",
    "release_year": 2013,
    "date": "2013-01-01T00:00:00.000Z",
    "review": {
      "rating": 4
    },
    "genres": [
      "Comedy",
      "Crime"
    ],
    "director": [
      "Rawson Marshall Thurber"
    ]
  },
  {
    "type": "movie",
    "title": "12 Years a Slave",
    "release_year": 2013,
    "date": "2013-01-01T00:00:00.000Z",
    "review": {
      "rating": 5
    },
    "genres": [
      "Biography",
      "Drama",
      "History"
    ],
    "director": [
      "Steve McQueen"
    ]
  },
  {
    "type": "movie",
    "title": "Iron Man 3",
    "release_year": 2013,
    "date": "2013-01-01T00:00:00.000Z",
    "review": {
      "rating": 3
    },
    "genres": [
      "Action",
      "Adventure",
      "Sci-Fi"
    ],
    "director": [
      "Shane Black"
    ]
  },
  {
    "type": "movie",
    "title": "World War Z",
    "release_year": 2013,
    "date": "2013-01-01T00:00:00.000Z",
    "review": {
      "rating": 3
    },
    "genres": [
      "Action",
      "Adventure",
      "Horror"
    ],
    "director": [
      "Marc Forster"
    ]
  },
  {
    "type": "movie",
    "title": "The Secret Life of Walter Mitty",
    "release_year": 2013,
    "date": "2013-01-01T00:00:00.000Z",
    "review": {
      "rating": 4
    },
    "genres": [
      "Adventure",
      "Comedy",
      "Drama"
    ],
    "director": [
      "Ben Stiller"
    ]
  },
  {
    "type": "movie",
    "title": "The Internship",
    "release_year": 2013,
    "date": "2013-01-01T00:00:00.000Z",
    "review": {
      "rating": 3
    },
    "genres": [
      "Comedy"
    ],
    "director": [
      "Shawn Levy"
    ]
  },
  {
    "type": "movie",
    "title": "This Is the End",
    "release_year": 2013,
    "date": "2013-01-01T00:00:00.000Z",
    "review": {
      "rating": 3
    },
    "genres": [
      "Comedy",
      "Fantasy"
    ],
    "director": [
      "Evan Goldberg",
      "Seth Rogen"
    ]
  },
  {
    "type": "movie",
    "title": "Enemy",
    "release_year": 2013,
    "date": "2013-01-01T00:00:00.000Z",
    "review": {
      "rating": 4
    },
    "genres": [
      "Drama",
      "Mystery",
      "Thriller"
    ],
    "director": [
      "Denis Villeneuve"
    ]
  },
  {
    "type": "movie",
    "title": "Pacific Rim",
    "release_year": 2013,
    "date": "2013-01-01T00:00:00.000Z",
    "review": {
      "rating": 2
    },
    "genres": [
      "Action",
      "Adventure",
      "Sci-Fi"
    ],
    "director": [
      "Guillermo del Toro"
    ]
  },
  {
    "type": "movie",
    "title": "Kick-Ass 2",
    "release_year": 2013,
    "date": "2013-01-01T00:00:00.000Z",
    "review": {
      "rating": 3
    },
    "genres": [
      "Action",
      "Comedy",
      "Crime"
    ],
    "director": [
      "Jeff Wadlow"
    ]
  },
  {
    "type": "movie",
    "title": "Rush",
    "release_year": 2013,
    "date": "2013-01-01T00:00:00.000Z",
    "review": {
      "rating": 3
    },
    "genres": [
      "Action",
      "Biography",
      "Drama"
    ],
    "director": [
      "Ron Howard"
    ]
  },
  {
    "type": "movie",
    "title": "Thor: The Dark World",
    "release_year": 2013,
    "date": "2013-01-01T00:00:00.000Z",
    "review": {
      "rating": 2
    },
    "genres": [
      "Action",
      "Adventure",
      "Fantasy"
    ],
    "director": [
      "Alan Taylor"
    ]
  },
  {
    "type": "movie",
    "title": "Warm Bodies",
    "release_year": 2013,
    "date": "2013-01-01T00:00:00.000Z",
    "review": {
      "rating": 2
    },
    "genres": [
      "Comedy",
      "Horror",
      "Romance"
    ],
    "director": [
      "Jonathan Levine"
    ]
  },
  {
    "type": "movie",
    "title": "The Purge",
    "release_year": 2013,
    "date": "2013-01-01T00:00:00.000Z",
    "review": {
      "rating": 1
    },
    "genres": [
      "Horror",
      "Sci-Fi",
      "Thriller"
    ],
    "director": [
      "James DeMonaco"
    ]
  },
  {
    "type": "movie",
    "title": "R.I.P.D.",
    "release_year": 2013,
    "date": "2013-01-01T00:00:00.000Z",
    "review": {
      "rating": 2
    },
    "genres": [
      "Action",
      "Adventure",
      "Comedy"
    ],
    "director": [
      "Robert Schwentke"
    ]
  },
  {
    "type": "movie",
    "title": "Don Jon",
    "release_year": 2013,
    "date": "2013-01-01T00:00:00.000Z",
    "review": {
      "rating": 3
    },
    "genres": [
      "Comedy",
      "Drama",
      "Romance"
    ],
    "director": [
      "Joseph Gordon-Levitt"
    ]
  },
  {
    "type": "movie",
    "title": "Pain & Gain",
    "release_year": 2013,
    "date": "2013-01-01T00:00:00.000Z",
    "review": {
      "rating": 3
    },
    "genres": [
      "Action",
      "Comedy",
      "Crime"
    ],
    "director": [
      "Michael Bay"
    ]
  },
  {
    "type": "movie",
    "title": "Elysium",
    "release_year": 2013,
    "date": "2013-01-01T00:00:00.000Z",
    "review": {
      "rating": 3
    },
    "genres": [
      "Action",
      "Drama",
      "Sci-Fi"
    ],
    "director": [
      "Neill Blomkamp"
    ]
  },
  {
    "type": "movie",
    "title": "The World's End",
    "release_year": 2013,
    "date": "2013-01-01T00:00:00.000Z",
    "review": {
      "rating": 3
    },
    "genres": [
      "Action",
      "Comedy",
      "Sci-Fi"
    ],
    "director": [
      "Edgar Wright"
    ]
  },
  {
    "type": "movie",
    "title": "The Wolverine",
    "release_year": 2013,
    "date": "2013-01-01T00:00:00.000Z",
    "review": {
      "rating": 4
    },
    "genres": [
      "Action",
      "Sci-Fi"
    ],
    "director": [
      "James Mangold"
    ]
  },
  {
    "type": "movie",
    "title": "Locke",
    "release_year": 2013,
    "date": "2013-01-01T00:00:00.000Z",
    "review": {
      "rating": 4
    },
    "genres": [
      "Drama"
    ],
    "director": [
      "Steven Knight"
    ]
  },
  {
    "type": "movie",
    "title": "The Hangover Part III",
    "release_year": 2013,
    "date": "2013-01-01T00:00:00.000Z",
    "review": {
      "rating": 3
    },
    "genres": [
      "Comedy",
      "Crime"
    ],
    "director": [
      "Todd Phillips"
    ]
  },
  {
    "type": "movie",
    "title": "Interstellar",
    "release_year": 2014,
    "date": "2014-01-01T00:00:00.000Z",
    "review": {
      "rating": 5
    },
    "genres": [
      "Adventure",
      "Drama",
      "Sci-Fi"
    ],
    "director": [
      "Christopher Nolan"
    ]
  },
  {
    "type": "movie",
    "title": "John Wick",
    "release_year": 2014,
    "date": "2014-01-01T00:00:00.000Z",
    "review": {
      "rating": 4
    },
    "genres": [
      "Action",
      "Crime",
      "Thriller"
    ],
    "director": [
      "Chad Stahelski",
      "David Leitch"
    ]
  },
  {
    "type": "movie",
    "title": "Whiplash",
    "release_year": 2014,
    "date": "2014-01-01T00:00:00.000Z",
    "review": {
      "rating": 5
    },
    "genres": [
      "Drama",
      "Music"
    ],
    "director": [
      "Damien Chazelle"
    ]
  },
  {
    "type": "movie",
    "title": "Guardians of the Galaxy",
    "release_year": 2014,
    "date": "2014-01-01T00:00:00.000Z",
    "review": {
      "rating": 4
    },
    "genres": [
      "Action",
      "Adventure",
      "Comedy"
    ],
    "director": [
      "James Gunn"
    ]
  },
  {
    "type": "movie",
    "title": "Kingsman: The Secret Service",
    "release_year": 2014,
    "date": "2014-01-01T00:00:00.000Z",
    "review": {
      "rating": 5
    },
    "genres": [
      "Action",
      "Adventure",
      "Comedy"
    ],
    "director": [
      "Matthew Vaughn"
    ]
  },
  {
    "type": "movie",
    "title": "Nightcrawler",
    "release_year": 2014,
    "date": "2014-01-01T00:00:00.000Z",
    "review": {
      "rating": 5
    },
    "genres": [
      "Crime",
      "Drama",
      "Thriller"
    ],
    "director": [
      "Dan Gilroy"
    ]
  },
  {
    "type": "movie",
    "title": "Edge of Tomorrow",
    "release_year": 2014,
    "date": "2014-01-01T00:00:00.000Z",
    "review": {
      "rating": 4
    },
    "genres": [
      "Action",
      "Adventure",
      "Sci-Fi"
    ],
    "director": [
      "Doug Liman"
    ]
  },
  {
    "type": "movie",
    "title": "Birdman",
    "release_year": null,
    "date": "2014-01-01T00:00:00.000Z",
    "review": {
      "rating": 3
    },
    "genres": [
      "Animation",
      "Action",
      "Adventure"
    ],
    "director": [
      "N/A"
    ]
  },
  {
    "type": "movie",
    "title": "Captain America: The Winter Soldier",
    "release_year": 2014,
    "date": "2014-01-01T00:00:00.000Z",
    "review": {
      "rating": 4
    },
    "genres": [
      "Action",
      "Adventure",
      "Sci-Fi"
    ],
    "director": [
      "Anthony Russo",
      "Joe Russo"
    ]
  },
  {
    "type": "movie",
    "title": "Big Hero 6",
    "release_year": 2014,
    "date": "2014-01-01T00:00:00.000Z",
    "review": {
      "rating": 4
    },
    "genres": [
      "Animation",
      "Action",
      "Adventure"
    ],
    "director": [
      "Don Hall",
      "Chris Williams"
    ]
  },
  {
    "type": "movie",
    "title": "NATURE VS MAN: Godzilla (1954)/Godzilla (2014)",
    "release_year": 1954,
    "date": "2014-01-01T00:00:00.000Z",
    "review": {
      "rating": 3
    },
    "genres": [
      "Talk-Show"
    ],
    "director": [
      "N/A"
    ]
  },
  {
    "type": "movie",
    "title": "X-Men: Days of Future Past",
    "release_year": 2014,
    "date": "2014-01-01T00:00:00.000Z",
    "review": {
      "rating": 4
    },
    "genres": [
      "Action",
      "Adventure",
      "Sci-Fi"
    ],
    "director": [
      "Bryan Singer"
    ]
  },
  {
    "type": "movie",
    "title": "The Lego Movie",
    "release_year": 2014,
    "date": "2014-01-01T00:00:00.000Z",
    "review": {
      "rating": 4
    },
    "genres": [
      "Animation",
      "Action",
      "Adventure"
    ],
    "director": [
      "Phil Lord",
      "Christopher Miller"
    ]
  },
  {
    "type": "movie",
    "title": "The Amazing Spider-Man 2",
    "release_year": 2014,
    "date": "2014-01-01T00:00:00.000Z",
    "review": {
      "rating": 3
    },
    "genres": [
      "Action",
      "Adventure",
      "Sci-Fi"
    ],
    "director": [
      "Marc Webb"
    ]
  },
  {
    "type": "movie",
    "title": "22 Jump Street",
    "release_year": 2014,
    "date": "2014-01-01T00:00:00.000Z",
    "review": {
      "rating": 3
    },
    "genres": [
      "Action",
      "Comedy",
      "Crime"
    ],
    "director": [
      "Phil Lord",
      "Christopher Miller"
    ]
  },
  {
    "type": "movie",
    "title": "300: Rise of an Empire",
    "release_year": 2014,
    "date": "2014-01-01T00:00:00.000Z",
    "review": {
      "rating": 2
    },
    "genres": [
      "Action",
      "Drama"
    ],
    "director": [
      "Noam Murro"
    ]
  },
  {
    "type": "movie",
    "title": "The Interview",
    "release_year": 2014,
    "date": "2014-01-01T00:00:00.000Z",
    "review": {
      "rating": 3
    },
    "genres": [
      "Action",
      "Adventure",
      "Comedy"
    ],
    "director": [
      "Evan Goldberg",
      "Seth Rogen"
    ]
  },
  {
    "type": "movie",
    "title": "The Theory of Everything",
    "release_year": 2014,
    "date": "2014-01-01T00:00:00.000Z",
    "review": {
      "rating": 4
    },
    "genres": [
      "Biography",
      "Drama",
      "Romance"
    ],
    "director": [
      "James Marsh"
    ]
  },
  {
    "type": "movie",
    "title": "The Fault in Our Stars",
    "release_year": 2014,
    "date": "2014-01-01T00:00:00.000Z",
    "review": {
      "rating": 4
    },
    "genres": [
      "Drama",
      "Romance"
    ],
    "director": [
      "Josh Boone"
    ]
  },
  {
    "type": "movie",
    "title": "Lucy",
    "release_year": 2014,
    "date": "2014-01-01T00:00:00.000Z",
    "review": {
      "rating": 2
    },
    "genres": [
      "Action",
      "Sci-Fi",
      "Thriller"
    ],
    "director": [
      "Luc Besson"
    ]
  },
  {
    "type": "movie",
    "title": "Boyhood",
    "release_year": 2014,
    "date": "2014-01-01T00:00:00.000Z",
    "review": {
      "rating": 3
    },
    "genres": [
      "Drama"
    ],
    "director": [
      "Richard Linklater"
    ]
  },
  {
    "type": "movie",
    "title": "Neighbors",
    "release_year": 2014,
    "date": "2014-01-01T00:00:00.000Z",
    "review": {
      "rating": 3
    },
    "genres": [
      "Comedy"
    ],
    "director": [
      "Nicholas Stoller"
    ]
  },
  {
    "type": "movie",
    "title": "Dawn of the Planet of the Apes",
    "release_year": 2014,
    "date": "2014-01-01T00:00:00.000Z",
    "review": {
      "rating": 4
    },
    "genres": [
      "Action",
      "Adventure",
      "Drama"
    ],
    "director": [
      "Matt Reeves"
    ]
  },
  {
    "type": "movie",
    "title": "Prisoners",
    "release_year": 2013,
    "date": "2014-01-01T00:00:00.000Z",
    "review": {
      "rating": 5
    },
    "genres": [
      "Crime",
      "Drama",
      "Mystery"
    ],
    "director": [
      "Denis Villeneuve"
    ]
  },
  {
    "type": "movie",
    "title": "The Imitation Game",
    "release_year": 2014,
    "date": "2014-01-01T00:00:00.000Z",
    "review": {
      "rating": 4
    },
    "genres": [
      "Biography",
      "Drama",
      "Thriller"
    ],
    "director": [
      "Morten Tyldum"
    ]
  },
  {
    "type": "movie",
    "title": "The Man from U.N.C.L.E.",
    "release_year": 2015,
    "date": "2015-01-01T00:00:00.000Z",
    "review": {
      "rating": 3
    },
    "genres": [
      "Action",
      "Adventure",
      "Comedy"
    ],
    "director": [
      "Guy Ritchie"
    ]
  },
  {
    "type": "movie",
    "title": "Sicario",
    "release_year": 2015,
    "date": "2015-01-01T00:00:00.000Z",
    "review": {
      "rating": 3
    },
    "genres": [
      "Action",
      "Crime",
      "Drama"
    ],
    "director": [
      "Denis Villeneuve"
    ]
  },
  {
    "type": "movie",
    "title": "Mad Max: Fury Road",
    "release_year": 2015,
    "date": "2015-01-01T00:00:00.000Z",
    "review": {
      "rating": 3
    },
    "genres": [
      "Action",
      "Adventure",
      "Sci-Fi"
    ],
    "director": [
      "George Miller"
    ]
  },
  {
    "type": "movie",
    "title": "Star Wars: Episode VII - The Force Awakens",
    "release_year": 2015,
    "date": "2015-01-01T00:00:00.000Z",
    "review": {
      "rating": 4
    },
    "genres": [
      "Action",
      "Adventure",
      "Sci-Fi"
    ],
    "director": [
      "J.J. Abrams"
    ]
  },
  {
    "type": "movie",
    "title": "The Hateful Eight",
    "release_year": 2015,
    "date": "2015-01-01T00:00:00.000Z",
    "review": {
      "rating": 5
    },
    "genres": [
      "Crime",
      "Drama",
      "Mystery"
    ],
    "director": [
      "Quentin Tarantino"
    ]
  },
  {
    "type": "movie",
    "title": "Jurassic World",
    "release_year": 2015,
    "date": "2015-01-01T00:00:00.000Z",
    "review": {
      "rating": 2
    },
    "genres": [
      "Action",
      "Adventure",
      "Sci-Fi"
    ],
    "director": [
      "Colin Trevorrow"
    ]
  },
  {
    "type": "movie",
    "title": "Avengers: Age of Ultron",
    "release_year": 2015,
    "date": "2015-01-01T00:00:00.000Z",
    "review": {
      "rating": 4
    },
    "genres": [
      "Action",
      "Adventure",
      "Sci-Fi"
    ],
    "director": [
      "Joss Whedon"
    ]
  },
  {
    "type": "movie",
    "title": "Legend",
    "release_year": 2015,
    "date": "2015-01-01T00:00:00.000Z",
    "review": {
      "rating": 4
    },
    "genres": [
      "Biography",
      "Crime",
      "Drama"
    ],
    "director": [
      "Brian Helgeland"
    ]
  },
  {
    "type": "movie",
    "title": "The Martian",
    "release_year": 2015,
    "date": "2015-01-01T00:00:00.000Z",
    "review": {
      "rating": 4
    },
    "genres": [
      "Adventure",
      "Drama",
      "Sci-Fi"
    ],
    "director": [
      "Ridley Scott"
    ]
  },
  {
    "type": "movie",
    "title": "Everest",
    "release_year": 2015,
    "date": "2015-01-01T00:00:00.000Z",
    "review": {
      "rating": 2
    },
    "genres": [
      "Action",
      "Adventure",
      "Biography"
    ],
    "director": [
      "Baltasar Kormákur"
    ]
  },
  {
    "type": "movie",
    "title": "Straight Outta Compton",
    "release_year": 2015,
    "date": "2015-01-01T00:00:00.000Z",
    "review": {
      "rating": 4
    },
    "genres": [
      "Biography",
      "Drama",
      "History"
    ],
    "director": [
      "F. Gary Gray"
    ]
  },
  {
    "type": "movie",
    "title": "Demolition",
    "release_year": 2015,
    "date": "2015-01-01T00:00:00.000Z",
    "review": {
      "rating": 4
    },
    "genres": [
      "Comedy",
      "Drama"
    ],
    "director": [
      "Jean-Marc Vallée"
    ]
  },
  {
    "type": "movie",
    "title": "Chappie",
    "release_year": 2015,
    "date": "2015-01-01T00:00:00.000Z",
    "review": {
      "rating": 4
    },
    "genres": [
      "Action",
      "Crime",
      "Drama"
    ],
    "director": [
      "Neill Blomkamp"
    ]
  },
  {
    "type": "movie",
    "title": "Dope",
    "release_year": 2015,
    "date": "2015-01-01T00:00:00.000Z",
    "review": {
      "rating": 2
    },
    "genres": [
      "Adventure",
      "Comedy",
      "Crime"
    ],
    "director": [
      "Rick Famuyiwa"
    ]
  },
  {
    "type": "movie",
    "title": "Hardcore Henry",
    "release_year": 2015,
    "date": "2015-01-01T00:00:00.000Z",
    "review": {
      "rating": 3
    },
    "genres": [
      "Action",
      "Adventure",
      "Sci-Fi"
    ],
    "director": [
      "Ilya Naishuller"
    ]
  },
  {
    "type": "movie",
    "title": "Deus Ex-machina",
    "release_year": 1995,
    "date": "2015-01-01T00:00:00.000Z",
    "review": {
      "rating": 5
    },
    "genres": [
      "Short"
    ],
    "director": [
      "Carlos Gerbase"
    ]
  },
  {
    "type": "movie",
    "title": "Rogue One: A Star Wars Story",
    "release_year": 2016,
    "date": "2016-01-01T00:00:00.000Z",
    "review": {
      "rating": 3
    },
    "genres": [
      "Action",
      "Adventure",
      "Sci-Fi"
    ],
    "director": [
      "Gareth Edwards"
    ]
  },
  {
    "type": "movie",
    "title": "Nocturnal Animals",
    "release_year": 2016,
    "date": "2016-01-01T00:00:00.000Z",
    "review": {
      "rating": 5
    },
    "genres": [
      "Drama",
      "Thriller"
    ],
    "director": [
      "Tom Ford"
    ]
  },
  {
    "type": "movie",
    "title": "Split",
    "release_year": 2016,
    "date": "2016-01-01T00:00:00.000Z",
    "review": {
      "rating": 3
    },
    "genres": [
      "Horror",
      "Thriller"
    ],
    "director": [
      "M. Night Shyamalan"
    ]
  },
  {
    "type": "movie",
    "title": "Deadpool",
    "release_year": 2016,
    "date": "2016-01-01T00:00:00.000Z",
    "review": {
      "rating": 5
    },
    "genres": [
      "Action",
      "Adventure",
      "Comedy"
    ],
    "director": [
      "Tim Miller"
    ]
  },
  {
    "type": "movie",
    "title": "Arrival",
    "release_year": 2016,
    "date": "2016-01-01T00:00:00.000Z",
    "review": {
      "rating": 5
    },
    "genres": [
      "Drama",
      "Mystery",
      "Sci-Fi"
    ],
    "director": [
      "Denis Villeneuve"
    ]
  },
  {
    "type": "movie",
    "title": "Hell or High Water",
    "release_year": 2016,
    "date": "2016-01-01T00:00:00.000Z",
    "review": {
      "rating": 3
    },
    "genres": [
      "Crime",
      "Drama",
      "Thriller"
    ],
    "director": [
      "David Mackenzie"
    ]
  },
  {
    "type": "movie",
    "title": "Captain Fantastic",
    "release_year": 2016,
    "date": "2016-01-01T00:00:00.000Z",
    "review": {
      "rating": 5
    },
    "genres": [
      "Comedy",
      "Drama"
    ],
    "director": [
      "Matt Ross"
    ]
  },
  {
    "type": "movie",
    "title": "Sausage Party",
    "release_year": 2016,
    "date": "2016-01-01T00:00:00.000Z",
    "review": {
      "rating": 2
    },
    "genres": [
      "Animation",
      "Adventure",
      "Comedy"
    ],
    "director": [
      "Greg Tiernan",
      "Conrad Vernon"
    ]
  },
  {
    "type": "movie",
    "title": "10 Cloverfield Lane",
    "release_year": 2016,
    "date": "2016-01-01T00:00:00.000Z",
    "review": {
      "rating": 4
    },
    "genres": [
      "Drama",
      "Horror",
      "Mystery"
    ],
    "director": [
      "Dan Trachtenberg"
    ]
  },
  {
    "type": "movie",
    "title": "Why Him?",
    "release_year": 2016,
    "date": "2016-01-01T00:00:00.000Z",
    "review": {
      "rating": 3
    },
    "genres": [
      "Comedy"
    ],
    "director": [
      "John Hamburg"
    ]
  },
  {
    "type": "movie",
    "title": "Snowden",
    "release_year": 2016,
    "date": "2016-01-01T00:00:00.000Z",
    "review": {
      "rating": 3
    },
    "genres": [
      "Biography",
      "Crime",
      "Drama"
    ],
    "director": [
      "Oliver Stone"
    ]
  },
  {
    "type": "movie",
    "title": "Spotlight",
    "release_year": 2015,
    "date": "2016-01-01T00:00:00.000Z",
    "review": {
      "rating": 4
    },
    "genres": [
      "Biography",
      "Crime",
      "Drama"
    ],
    "director": [
      "Tom McCarthy"
    ]
  },
  {
    "type": "movie",
    "title": "Batman v Superman: Dawn of Justice",
    "release_year": 2016,
    "date": "2016-03-22T00:00:00.000Z",
    "review": {
      "rating": 2
    },
    "genres": [
      "Action",
      "Adventure",
      "Sci-Fi",
      "Comicbook"
    ],
    "director": [
      "Zack Snyder"
    ]
  },
  {
    "type": "movie",
    "title": "Captain America: Civil War",
    "release_year": 2016,
    "date": "2016-04-26T00:00:00.000Z",
    "review": {
      "rating": 4
    },
    "genres": [
      "Action",
      "Adventure",
      "Sci-Fi",
      "Comicbook"
    ],
    "director": [
      "Russo Brothers"
    ]
  },
  {
    "type": "movie",
    "title": "X-Men: Apocalypse",
    "release_year": 2016,
    "date": "2016-05-20T00:00:00.000Z",
    "review": {
      "rating": 2
    },
    "genres": [
      "Action",
      "Adventure",
      "Sci-Fi",
      "Comicbook"
    ],
    "director": [
      "Bryan Singer"
    ]
  },
  {
    "type": "movie",
    "title": "Warcraft",
    "release_year": 2016,
    "date": "2016-05-27T00:00:00.000Z",
    "review": {
      "rating": 1
    },
    "genres": [
      "Action",
      "Adventure",
      "Fantasy"
    ],
    "director": [
      "Duncan Jones"
    ]
  },
  {
    "type": "movie",
    "title": "War Dogs",
    "release_year": 2016,
    "date": "2016-08-19T00:00:00.000Z",
    "review": {
      "rating": 3
    },
    "genres": [
      "Biography",
      "Crime",
      "Comedy",
      "Drama",
      "War"
    ],
    "director": [
      "Todd Phillips"
    ]
  },
  {
    "type": "movie",
    "title": "Doctor Strange",
    "release_year": 2016,
    "date": "2016-11-04T00:00:00.000Z",
    "review": {
      "rating": 3
    },
    "genres": [
      "Action",
      "Adventure",
      "Sci-Fi",
      "Comicbook",
      "Fantasy"
    ],
    "director": [
      "Scott Derrickson"
    ]
  },
  {
    "type": "movie",
    "title": "Blade Runner 2049",
    "release_year": 2017,
    "date": "2017-01-01T00:00:00.000Z",
    "review": {
      "rating": 5
    },
    "genres": [
      "Action",
      "Drama",
      "Mystery"
    ],
    "director": [
      "Denis Villeneuve"
    ]
  },
  {
    "type": "movie",
    "title": "Get Out",
    "release_year": 2017,
    "date": "2017-01-01T00:00:00.000Z",
    "review": {
      "rating": 4
    },
    "genres": [
      "Horror",
      "Mystery",
      "Thriller"
    ],
    "director": [
      "Jordan Peele"
    ]
  },
  {
    "type": "movie",
    "title": "John Wick: Chapter 2",
    "release_year": 2017,
    "date": "2017-01-01T00:00:00.000Z",
    "review": {
      "rating": 4
    },
    "genres": [
      "Action",
      "Crime",
      "Thriller"
    ],
    "director": [
      "Chad Stahelski"
    ]
  },
  {
    "type": "movie",
    "title": "Star Wars: Episode VIII - The Last Jedi",
    "release_year": 2017,
    "date": "2017-01-01T00:00:00.000Z",
    "review": {
      "rating": 2
    },
    "genres": [
      "Action",
      "Adventure",
      "Fantasy"
    ],
    "director": [
      "Rian Johnson"
    ]
  },
  {
    "type": "movie",
    "title": "Baby Driver",
    "release_year": 2017,
    "date": "2017-01-01T00:00:00.000Z",
    "review": {
      "rating": 4
    },
    "genres": [
      "Action",
      "Crime",
      "Drama"
    ],
    "director": [
      "Edgar Wright"
    ]
  },
  {
    "type": "movie",
    "title": "It (2017)",
    "release_year": 2017,
    "date": "2017-01-01T00:00:00.000Z",
    "review": {
      "rating": 3
    },
    "genres": [
      "Comedy",
      "Talk-Show"
    ],
    "director": [
      "Sol Harris",
      "Allen Turing"
    ]
  },
  {
    "type": "movie",
    "title": "Wonder Woman",
    "release_year": 2017,
    "date": "2017-01-01T00:00:00.000Z",
    "review": {
      "rating": 2
    },
    "genres": [
      "Action",
      "Adventure",
      "Fantasy"
    ],
    "director": [
      "Patty Jenkins"
    ]
  },
  {
    "type": "movie",
    "title": "The Shape of Water",
    "release_year": 2017,
    "date": "2017-01-01T00:00:00.000Z",
    "review": {
      "rating": 3
    },
    "genres": [
      "Drama",
      "Fantasy",
      "Romance"
    ],
    "director": [
      "Guillermo del Toro"
    ]
  },
  {
    "type": "movie",
    "title": "Kong: Skull Island",
    "release_year": 2017,
    "date": "2017-01-01T00:00:00.000Z",
    "review": {
      "rating": 3
    },
    "genres": [
      "Action",
      "Adventure",
      "Fantasy"
    ],
    "director": [
      "Jordan Vogt-Roberts"
    ]
  },
  {
    "type": "movie",
    "title": "Good-Time Girl",
    "release_year": 1948,
    "date": "2017-01-01T00:00:00.000Z",
    "review": {
      "rating": 3
    },
    "genres": [
      "Crime",
      "Drama"
    ],
    "director": [
      "David MacDonald"
    ]
  },
  {
    "type": "movie",
    "title": "War for the Planet of the Apes",
    "release_year": 2017,
    "date": "2017-01-01T00:00:00.000Z",
    "review": {
      "rating": 4
    },
    "genres": [
      "Action",
      "Adventure",
      "Drama"
    ],
    "director": [
      "Matt Reeves"
    ]
  },
  {
    "type": "movie",
    "title": "The Disaster Artist",
    "release_year": 2017,
    "date": "2017-01-01T00:00:00.000Z",
    "review": {
      "rating": 3
    },
    "genres": [
      "Biography",
      "Comedy",
      "Drama"
    ],
    "director": [
      "James Franco"
    ]
  },
  {
    "type": "movie",
    "title": "13 Hours",
    "release_year": 2016,
    "date": "2017-01-01T00:00:00.000Z",
    "review": {
      "rating": 4
    },
    "genres": [
      "Action",
      "Drama",
      "History"
    ],
    "director": [
      "Michael Bay"
    ]
  },
  {
    "type": "movie",
    "title": "Paper Towns",
    "release_year": 2015,
    "date": "2017-01-01T00:00:00.000Z",
    "review": {
      "rating": 3
    },
    "genres": [
      "Adventure",
      "Comedy",
      "Drama"
    ],
    "director": [
      "Jake Schreier"
    ]
  },
  {
    "type": "movie",
    "title": "Logan",
    "release_year": 2017,
    "date": "2017-03-01T00:00:00.000Z",
    "review": {
      "rating": 5
    },
    "genres": [
      "Action",
      "Drama",
      "Sci-Fi",
      "Comicbook",
      "Thriller"
    ],
    "director": [
      "James Mangold"
    ]
  },
  {
    "type": "movie",
    "title": "Guardians of the Galaxy Vol. 2",
    "release_year": 2017,
    "date": "2017-04-26T00:00:00.000Z",
    "review": {
      "rating": 3
    },
    "genres": [
      "Action",
      "Adventure",
      "Sci-Fi",
      "Comicbook",
      "Comedy"
    ],
    "director": [
      "James Gunn"
    ]
  },
  {
    "type": "movie",
    "title": "Spider-Man: Homecoming ",
    "release_year": 2017,
    "date": "2017-07-07T00:00:00.000Z",
    "review": {
      "rating": 4
    },
    "genres": [
      "Action",
      "Adventure",
      "Sci-Fi",
      "Comicbook"
    ],
    "director": [
      "Jon Watts"
    ]
  },
  {
    "type": "movie",
    "title": "Thor: Ragnarok",
    "release_year": 2017,
    "date": "2017-10-27T00:00:00.000Z",
    "review": {
      "rating": 4
    },
    "genres": [
      "Action",
      "Adventure",
      "Fantasy",
      "Sci-Fi",
      "Comicbook",
      "Comedy"
    ],
    "director": [
      "Taika Watiti"
    ]
  },
  {
    "type": "movie",
    "title": "Justice League",
    "release_year": 2017,
    "date": "2017-11-15T00:00:00.000Z",
    "review": {
      "rating": 2
    },
    "genres": [
      "Action",
      "Adventure",
      "Fantasy",
      "Sci-Fi",
      "Comicbook"
    ],
    "director": [
      "Zack Snyder",
      "Josh Whedon"
    ]
  },
  {
    "type": "movie",
    "title": "Wind River",
    "release_year": 2017,
    "date": "2017-11-29T00:00:00.000Z",
    "review": {
      "rating": 4
    },
    "genres": [
      "Crime",
      "Drama",
      "Mystery"
    ],
    "director": [
      "Taylor Sheridan"
    ]
  },
  {
    "type": "movie",
    "title": "Black Panther",
    "release_year": 2018,
    "date": "2018-01-01T00:00:00.000Z",
    "review": {
      "rating": 4
    },
    "genres": [
      "Action",
      "Adventure",
      "Sci-Fi"
    ],
    "director": [
      "Ryan Coogler"
    ]
  },
  {
    "type": "movie",
    "title": "A Quiet Place",
    "release_year": 2018,
    "date": "2018-01-01T00:00:00.000Z",
    "review": {
      "rating": 5
    },
    "genres": [
      "Drama",
      "Horror",
      "Sci-Fi"
    ],
    "director": [
      "John Krasinski"
    ]
  },
  {
    "type": "movie",
    "title": "Avengers: Infinity War",
    "release_year": 2018,
    "date": "2018-01-01T00:00:00.000Z",
    "review": {
      "rating": 4
    },
    "genres": [
      "Action",
      "Adventure",
      "Sci-Fi"
    ],
    "director": [
      "Anthony Russo",
      "Joe Russo"
    ]
  },
  {
    "type": "movie",
    "title": "Ready Player One",
    "release_year": 2018,
    "date": "2018-01-01T00:00:00.000Z",
    "review": {
      "rating": 3
    },
    "genres": [
      "Action",
      "Adventure",
      "Sci-Fi"
    ],
    "director": [
      "Steven Spielberg"
    ]
  },
  {
    "type": "movie",
    "title": "Deadpool 2",
    "release_year": 2018,
    "date": "2018-01-01T00:00:00.000Z",
    "review": {
      "rating": 4
    },
    "genres": [
      "Action",
      "Adventure",
      "Comedy"
    ],
    "director": [
      "David Leitch"
    ]
  },
  {
    "type": "movie",
    "title": "Aquaman",
    "release_year": 2018,
    "date": "2018-01-01T00:00:00.000Z",
    "review": {
      "rating": 3
    },
    "genres": [
      "Action",
      "Adventure",
      "Fantasy"
    ],
    "director": [
      "James Wan"
    ]
  },
  {
    "type": "movie",
    "title": "Annihilation",
    "release_year": 2018,
    "date": "2018-01-01T00:00:00.000Z",
    "review": {
      "rating": 3
    },
    "genres": [
      "Adventure",
      "Drama",
      "Horror"
    ],
    "director": [
      "Alex Garland"
    ]
  },
  {
    "type": "movie",
    "title": "Game Night",
    "release_year": 2018,
    "date": "2018-01-01T00:00:00.000Z",
    "review": {
      "rating": 2
    },
    "genres": [
      "Action",
      "Adventure",
      "Comedy"
    ],
    "director": [
      "John Francis Daley",
      "Jonathan Goldstein"
    ]
  },
  {
    "type": "movie",
    "title": "Venom",
    "release_year": 2018,
    "date": "2018-01-01T00:00:00.000Z",
    "review": {
      "rating": 2
    },
    "genres": [
      "Action",
      "Adventure",
      "Sci-Fi"
    ],
    "director": [
      "Ruben Fleischer"
    ]
  },
  {
    "type": "movie",
    "title": "BlacKkKlansman",
    "release_year": 2018,
    "date": "2018-01-01T00:00:00.000Z",
    "review": {
      "rating": 3
    },
    "genres": [
      "Biography",
      "Comedy",
      "Crime"
    ],
    "director": [
      "Spike Lee"
    ]
  },
  {
    "type": "movie",
    "title": "Upgrade",
    "release_year": 2018,
    "date": "2018-01-01T00:00:00.000Z",
    "review": {
      "rating": 5
    },
    "genres": [
      "Action",
      "Sci-Fi",
      "Thriller"
    ],
    "director": [
      "Leigh Whannell"
    ]
  },
  {
    "type": "movie",
    "title": "Ant-Man and The Wasp",
    "release_year": 2018,
    "date": "2018-07-04T00:00:00.000Z",
    "review": {
      "rating": 3
    },
    "genres": [
      "Action",
      "Adventure",
      "Comedy",
      "Sci-Fi",
      "Comicbook"
    ],
    "director": [
      "Peyton Reed"
    ]
  },
  {
    "type": "movie",
    "title": "Mission: Impossible - Fallout",
    "release_year": 2018,
    "date": "2018-08-14T00:00:00.000Z",
    "review": {
      "rating": 3
    },
    "genres": [
      "Action",
      "Adventure",
      "Thriller"
    ],
    "director": [
      "Christopher McQuarrie"
    ]
  },
  {
    "type": "movie",
    "title": "Incredibles 2",
    "release_year": 2018,
    "date": "2018-08-24T00:00:00.000Z",
    "review": {
      "rating": 4
    },
    "genres": [
      "Action",
      "Adventure",
      "Sci-Fi",
      "Comicbook",
      "Family",
      "Animation"
    ],
    "director": [
      "Brad Bird"
    ]
  },
  {
    "type": "movie",
    "title": "Spider-Man: Into The Spider-Verse",
    "release_year": 2018,
    "date": "2018-12-17T00:00:00.000Z",
    "review": {
      "rating": 5
    },
    "genres": [
      "Action",
      "Adventure",
      "Sci-Fi",
      "Comicbook",
      "Fantasy",
      "Animation"
    ],
    "director": [
      "Bob Persichetti",
      "Peter Ramsey",
      "Rodney Rothman"
    ]
  },
  {
    "type": "movie",
    "title": "Once Upon a Time in Hollywood",
    "release_year": 2019,
    "date": "2019-01-01T00:00:00.000Z",
    "review": {
      "rating": 5
    },
    "genres": [
      "Comedy",
      "Drama"
    ],
    "director": [
      "Quentin Tarantino"
    ]
  },
  {
    "type": "movie",
    "title": "Midsommar",
    "release_year": 2019,
    "date": "2019-01-01T00:00:00.000Z",
    "review": {
      "rating": 5
    },
    "genres": [
      "Drama",
      "Horror",
      "Mystery"
    ],
    "director": [
      "Ari Aster"
    ]
  },
  {
    "type": "movie",
    "title": "John Wick: Chapter 3 - Parabellum",
    "release_year": 2019,
    "date": "2019-01-01T00:00:00.000Z",
    "review": {
      "rating": 3
    },
    "genres": [
      "Action",
      "Crime",
      "Thriller"
    ],
    "director": [
      "Chad Stahelski"
    ]
  },
  {
    "type": "movie",
    "title": "Captain Marvel",
    "release_year": 2019,
    "date": "2019-01-01T00:00:00.000Z",
    "review": {
      "rating": 3
    },
    "genres": [
      "Action",
      "Adventure",
      "Sci-Fi"
    ],
    "director": [
      "Anna Boden",
      "Ryan Fleck"
    ]
  },
  {
    "type": "movie",
    "title": "El Camino: A Breaking Bad Movie",
    "release_year": 2019,
    "date": "2019-01-01T00:00:00.000Z",
    "review": {
      "rating": 5
    },
    "genres": [
      "Action",
      "Crime",
      "Drama"
    ],
    "director": [
      "Vince Gilligan"
    ]
  },
  {
    "type": "movie",
    "title": "Avengers: Endgame",
    "release_year": 2019,
    "date": "2019-04-24T00:00:00.000Z",
    "review": {
      "rating": 5
    },
    "genres": [
      "Action",
      "Adventure",
      "Sci-Fi",
      "Comicbook",
      "Drama"
    ],
    "director": [
      "Russo Brothers"
    ]
  },
  {
    "type": "movie",
    "title": "Spider-Man: Far From Home",
    "release_year": 2019,
    "date": "2019-07-04T00:00:00.000Z",
    "review": {
      "rating": 4
    },
    "genres": [
      "Action",
      "Adventure",
      "Sci-Fi",
      "Comicbook"
    ],
    "director": [
      "Jon Watts"
    ]
  },
  {
    "type": "movie",
    "title": "Joker",
    "release_year": 2019,
    "date": "2019-10-04T00:00:00.000Z",
    "review": {
      "rating": 4
    },
    "genres": [
      "Crime",
      "Drama",
      "Thriller"
    ],
    "director": [
      "Todd Phillips"
    ]
  },
  {
    "type": "movie",
    "title": "Toy Story 4",
    "release_year": 2019,
    "date": "2019-10-07T00:00:00.000Z",
    "review": {
      "rating": 3
    },
    "genres": [
      "Animation",
      "Adventure",
      "Comedy",
      "Family",
      "Fantasy"
    ],
    "director": [
      "Josh Cooley"
    ]
  },
  {
    "type": "movie",
    "title": "Knives Out",
    "release_year": 2019,
    "date": "2019-12-06T00:00:00.000Z",
    "review": {
      "rating": 5
    },
    "genres": [
      "Comedy",
      "Drama",
      "Mystery",
      "Crime",
      "Thriller"
    ],
    "director": [
      "Rian Johnson"
    ]
  },
  {
    "type": "movie",
    "title": "1917",
    "release_year": 2020,
    "date": "2020-02-05T00:00:00.000Z",
    "review": {
      "rating": 4
    },
    "genres": [
      "Action",
      "Drama",
      "War"
    ],
    "director": [
      "Sam Mendes"
    ]
  },
  {
    "type": "movie",
    "title": "Birds of Prey",
    "release_year": 2020,
    "date": "2020-02-08T00:00:00.000Z",
    "review": {
      "rating": 2
    },
    "genres": [
      "Comedy",
      "Action",
      "Adventure",
      "Crime",
      "Comicbook"
    ],
    "director": [
      "Cathy Yan"
    ]
  },
  {
    "type": "movie",
    "title": "Parasite",
    "release_year": 2019,
    "date": "2020-02-22T00:00:00.000Z",
    "review": {
      "rating": 4
    },
    "genres": [
      "Comedy",
      "Drama",
      "Thriller"
    ],
    "director": [
      "Bong Joon Ho"
    ]
  },
  {
    "type": "movie",
    "title": "Jojo Rabbit",
    "release_year": 2019,
    "date": "2020-03-04T00:00:00.000Z",
    "review": {
      "rating": 5
    },
    "genres": [
      "Comedy",
      "Drama",
      "War"
    ],
    "director": [
      "Taika Watiti"
    ]
  },
  {
    "type": "movie",
    "title": "The Invisible Man",
    "release_year": 2020,
    "date": "2020-03-30T00:00:00.000Z",
    "review": {
      "rating": 4
    },
    "genres": [
      "Drama",
      "Horror",
      "Thriller",
      "Sci-Fi",
      "Mystery"
    ],
    "director": [
      "Leigh Whannell"
    ]
  },
  {
    "type": "movie",
    "title": "The Gentlemen",
    "release_year": 2019,
    "date": "2020-04-03T00:00:00.000Z",
    "review": {
      "rating": 4
    },
    "genres": [
      "Action",
      "Comedy",
      "Crime"
    ],
    "director": [
      "Guy Ritchie"
    ]
  },
  {
    "type": "movie",
    "title": "Spies in Disguise",
    "release_year": 2019,
    "date": "2020-04-07T00:00:00.000Z",
    "review": {
      "rating": 3
    },
    "genres": [
      "Action",
      "Comedy",
      "Adventure",
      "Animation",
      "Family",
      "Fantasy",
      "Thriller",
      "Sci-Fi"
    ],
    "director": [
      "Nick Bruno",
      "Troy Quane"
    ]
  },
  {
    "type": "movie",
    "title": "Bad Boys For Life",
    "release_year": 2020,
    "date": "2020-04-10T00:00:00.000Z",
    "review": {
      "rating": 3
    },
    "genres": [
      "Action",
      "Comedy",
      "Crime",
      "Thriller"
    ],
    "director": [
      "Adil El Arbi",
      "Bilall Fallah"
    ]
  },
  {
    "type": "movie",
    "title": "The Big Sick",
    "release_year": 2017,
    "date": "2020-04-17T00:00:00.000Z",
    "review": {
      "rating": 4
    },
    "genres": [
      "Comedy",
      "Drama",
      "Romance"
    ],
    "director": [
      "Michael Showalter"
    ]
  },
  {
    "type": "movie",
    "title": "Johnny English Strikes Again",
    "release_year": 2018,
    "date": "2020-06-05T00:00:00.000Z",
    "review": {
      "rating": 3
    },
    "genres": [
      "Comedy",
      "Action",
      "Adventure"
    ],
    "director": [
      "David Kerr"
    ]
  },
  {
    "type": "movie",
    "title": "Minority Report",
    "release_year": 2002,
    "date": "2020-06-06T00:00:00.000Z",
    "review": {
      "rating": 3
    },
    "genres": [
      "Action",
      "Crime",
      "Mystery",
      "Thriller",
      "Sci-Fi"
    ],
    "director": [
      "Steven Spielberg"
    ]
  },
  {
    "type": "movie",
    "title": "Mean Girls",
    "release_year": 2004,
    "date": "2020-06-07T00:00:00.000Z",
    "review": {
      "rating": 3
    },
    "genres": [
      "Comedy"
    ],
    "director": [
      "Mark Waters"
    ]
  },
  {
    "type": "movie",
    "title": "The King of Staten Island",
    "release_year": 2020,
    "date": "2020-06-15T00:00:00.000Z",
    "review": {
      "rating": 4
    },
    "genres": [
      "Comedy",
      "Drama"
    ],
    "director": [
      "Judd Apatow"
    ]
  },
  {
    "type": "movie",
    "title": "Extraction",
    "release_year": 2020,
    "date": "2020-07-20T00:00:00.000Z",
    "review": {
      "rating": 3
    },
    "genres": [
      "Action",
      "Thriller"
    ],
    "director": [
      "Sam Hargrave"
    ]
  },
  {
    "type": "movie",
    "title": "The Rental",
    "release_year": 2020,
    "date": "2020-07-30T00:00:00.000Z",
    "review": {
      "rating": 3
    },
    "genres": [
      "Drama",
      "Horror",
      "Thriller",
      "Mystery"
    ],
    "director": [
      "Dave Franco"
    ]
  },
  {
    "type": "movie",
    "title": "Uncut Gems",
    "release_year": 2019,
    "date": "2020-08-19T00:00:00.000Z",
    "review": {
      "rating": 4
    },
    "genres": [
      "Crime",
      "Drama",
      "Thriller"
    ],
    "director": [
      "Benny Safdie",
      "Josh Safdie"
    ]
  },
  {
    "type": "movie",
    "title": "Room",
    "release_year": 2015,
    "date": "2020-08-23T00:00:00.000Z",
    "review": {
      "rating": 4
    },
    "genres": [
      "Drama",
      "Thriller"
    ],
    "director": [
      "Lenny Abrahamson"
    ]
  },
  {
    "type": "movie",
    "title": "Tenet",
    "release_year": 2020,
    "date": "2020-08-26T00:00:00.000Z",
    "review": {
      "rating": 4
    },
    "genres": [
      "Action",
      "Sci-Fi",
      "Thriller"
    ],
    "director": [
      "Christopher Nolan"
    ]
  },
  {
    "type": "movie",
    "title": "Onward",
    "release_year": 2020,
    "date": "2020-08-28T00:00:00.000Z",
    "review": {
      "rating": 3
    },
    "genres": [
      "Animation",
      "Adventure",
      "Fantasy",
      "Comedy",
      "Family"
    ],
    "director": [
      "Dan Scanlon"
    ]
  },
  {
    "type": "movie",
    "title": "The Incredible Journey",
    "release_year": 1963,
    "date": "2020-09-20T00:00:00.000Z",
    "review": {
      "rating": 3
    },
    "genres": [
      "Adventure",
      "Drama",
      "Family"
    ],
    "director": [
      "Fletcher Markle"
    ]
  },
  {
    "type": "movie",
    "title": "Borat Subsequent Moviefilm",
    "release_year": 2020,
    "date": "2020-10-23T00:00:00.000Z",
    "review": {
      "rating": 4
    },
    "genres": [
      "Comedy"
    ],
    "director": [
      "Jason Woliner"
    ]
  },
  {
    "type": "movie",
    "title": "Love and Monsters",
    "release_year": 2020,
    "date": "2020-10-29T00:00:00.000Z",
    "review": {
      "rating": 3
    },
    "genres": [
      "Action",
      "Adventure",
      "Comedy",
      "Fantasy",
      "Sci-Fi"
    ],
    "director": [
      "Michael Matthews"
    ]
  },
  {
    "type": "movie",
    "title": "Yesterday",
    "release_year": 2019,
    "date": "2021-02-19T00:00:00.000Z",
    "review": {
      "rating": 4
    },
    "genres": [
      "Comedy",
      "Fantasy",
      "Music",
      "Romance"
    ],
    "director": [
      "Danny Boyle"
    ]
  },
  {
    "type": "movie",
    "title": "This is 40",
    "release_year": 2012,
    "date": "2021-02-28T00:00:00.000Z",
    "review": {
      "rating": 4
    },
    "genres": [
      "Comedy",
      "Romance"
    ],
    "director": [
      "Judd Apatow"
    ]
  },
  {
    "type": "movie",
    "title": "Zack Snyder's Justice League",
    "release_year": 2021,
    "date": "2021-03-18T00:00:00.000Z",
    "review": {
      "rating": 4
    },
    "genres": [
      "Action",
      "Adventure",
      "Fantasy",
      "Sci-Fi",
      "Comicbook"
    ],
    "director": [
      "Zack Snyder"
    ]
  },
  {
    "type": "movie",
    "title": "Deadly Illusions",
    "release_year": 2021,
    "date": "2021-03-26T00:00:00.000Z",
    "review": {
      "rating": 1
    },
    "genres": [
      "Drama",
      "Thriller"
    ],
    "director": [
      "Anna Elizabeth James"
    ]
  },
  {
    "type": "movie",
    "title": "Bad Trip",
    "release_year": 2021,
    "date": "2021-03-28T00:00:00.000Z",
    "review": {
      "rating": 3
    },
    "genres": [
      "Comedy"
    ],
    "director": [
      "Kitao Sakurai"
    ]
  },
  {
    "type": "movie",
    "title": "Stowaway",
    "release_year": 2021,
    "date": "2021-04-24T00:00:00.000Z",
    "review": {
      "rating": 3
    },
    "genres": [
      "Adventure",
      "Sci-Fi",
      "Thriller"
    ],
    "director": [
      "Joe Penna"
    ]
  },
  {
    "type": "movie",
    "title": "Bo Burnham: Inside",
    "release_year": 2021,
    "date": "2021-06-07T00:00:00.000Z",
    "review": {
      "rating": 5
    },
    "genres": [
      "Comedy",
      "Drama",
      "Music"
    ],
    "director": [
      "Bo Burnhamn"
    ]
  },
  {
    "type": "movie",
    "title": "A Quiet Place Part II",
    "release_year": 2021,
    "date": "2021-06-09T00:00:00.000Z",
    "review": {
      "rating": 5
    },
    "genres": [
      "Drama",
      "Sci-Fi",
      "Horror",
      "Thriller"
    ],
    "director": [
      "John Krasinski"
    ]
  },
  {
    "type": "movie",
    "title": "Black Widow",
    "release_year": 2021,
    "date": "2021-07-07T00:00:00.000Z",
    "review": {
      "rating": 3
    },
    "genres": [
      "Action",
      "Adventure",
      "Sci-Fi",
      "Comicbook"
    ],
    "director": [
      "Cate Shortland"
    ]
  },
  {
    "type": "movie",
    "title": "The Suicide Squad",
    "release_year": 2021,
    "date": "2021-08-06T00:00:00.000Z",
    "review": {
      "rating": 4
    },
    "genres": [
      "Action",
      "Adventure",
      "Comedy",
      "Sci-Fi",
      "Comicbook"
    ],
    "director": [
      "James Gunn"
    ]
  },
  {
    "type": "movie",
    "title": "Free Guy",
    "release_year": 2021,
    "date": "2021-08-21T00:00:00.000Z",
    "review": {
      "rating": 4
    },
    "genres": [
      "Action",
      "Adventure",
      "Comedy",
      "Sci-Fi"
    ],
    "director": [
      "Shawn Levy"
    ]
  },
  {
    "type": "movie",
    "title": "Shang-Chi and the Legend of the Ten Rings",
    "release_year": 2021,
    "date": "2021-09-01T00:00:00.000Z",
    "review": {
      "rating": 4
    },
    "genres": [
      "Action",
      "Adventure",
      "Sci-Fi",
      "Fantasy",
      "Comicbook"
    ],
    "director": [
      "Destin Daniel Cretton"
    ]
  },
  {
    "type": "movie",
    "title": "Dune",
    "release_year": 2021,
    "date": "2021-10-11T00:00:00.000Z",
    "review": {
      "rating": 4
    },
    "genres": [
      "Action",
      "Adventure",
      "Sci-Fi",
      "Drama"
    ],
    "director": [
      "Denis Villeneuve"
    ]
  },
  {
    "type": "movie",
    "title": "Eternals",
    "release_year": 2021,
    "date": "2021-11-03T00:00:00.000Z",
    "review": {
      "rating": 3
    },
    "genres": [
      "Action",
      "Adventure",
      "Sci-Fi",
      "Comicbook",
      "Fantasy"
    ],
    "director": [
      "Chloé Zhao"
    ]
  },
  {
    "type": "movie",
    "title": "Venom: Let There Be Carnage",
    "release_year": 2021,
    "date": "2021-11-13T00:00:00.000Z",
    "review": {
      "rating": 3
    },
    "genres": [
      "Action",
      "Adventure",
      "Sci-Fi",
      "Comicbook",
      "Thriller"
    ],
    "director": [
      "Andy Serkis"
    ]
  },
  {
    "type": "movie",
    "title": "Love Hard",
    "release_year": 2021,
    "date": "2021-11-27T00:00:00.000Z",
    "review": {
      "rating": 3
    },
    "genres": [
      "Comedy",
      "Romance"
    ],
    "director": [
      "Hernan Jimenez"
    ]
  },
  {
    "type": "movie",
    "title": "Atomic Blonde",
    "release_year": 2017,
    "date": "2021-12-17T00:00:00.000Z",
    "review": {
      "rating": 3
    },
    "genres": [
      "Action",
      "Thriller"
    ],
    "director": [
      "David Leitch"
    ]
  },
  {
    "type": "movie",
    "title": "Spider-Man: No Way Home",
    "release_year": 2021,
    "date": "2021-12-19T00:00:00.000Z",
    "review": {
      "rating": 5
    },
    "genres": [
      "Action",
      "Adventure",
      "Comedy",
      "Comicbook"
    ],
    "director": [
      "Jon Watts"
    ]
  },
  {
    "type": "movie",
    "title": "The Green Knight",
    "release_year": 2021,
    "date": "2022-01-09T00:00:00.000Z",
    "review": {
      "rating": 3
    },
    "genres": [
      "Adventure",
      "Drama",
      "Fantasy"
    ],
    "director": [
      "David Lowery"
    ]
  },
  {
    "type": "movie",
    "title": "The Matrix Resurrections",
    "release_year": 2021,
    "date": "2022-01-15T00:00:00.000Z",
    "review": {
      "rating": 2
    },
    "genres": [
      "Action",
      "Sci-Fi"
    ],
    "director": [
      "Lana Wachowski"
    ]
  },
  {
    "type": "movie",
    "title": "Ant-Man",
    "release_year": 2015,
    "date": "2022-02-06T00:00:00.000Z",
    "review": {
      "rating": 3
    },
    "genres": [
      "Action",
      "Adventure",
      "Comedy",
      "Sci-Fi",
      "Comicbook"
    ],
    "director": [
      "Peyton Reed"
    ]
  },
  {
    "type": "movie",
    "title": "Chicken Run",
    "release_year": 2000,
    "date": "2022-02-06T00:00:00.000Z",
    "review": {
      "rating": 4
    },
    "genres": [
      "Animation",
      "Adventure",
      "Comedy",
      "Drama",
      "Family"
    ],
    "director": [
      "Peter Lord",
      "Nick Park"
    ]
  },
  {
    "type": "movie",
    "title": "The Tinder Swindler",
    "release_year": 2022,
    "date": "2022-02-07T00:00:00.000Z",
    "review": {
      "rating": 4
    },
    "genres": [
      "Documentary",
      "Crime"
    ],
    "director": [
      "Felicity Morris"
    ]
  },
  {
    "type": "movie",
    "title": "Red Notice",
    "release_year": 2021,
    "date": "2022-02-19T00:00:00.000Z",
    "review": {
      "rating": 3
    },
    "genres": [
      "Action",
      "Comedy",
      "Thriller"
    ],
    "director": [
      "Rawson Marshall Thurber"
    ]
  },
  {
    "type": "movie",
    "title": "The Batman",
    "release_year": 2022,
    "date": "2022-03-06T00:00:00.000Z",
    "review": {
      "rating": 5
    },
    "genres": [
      "Action",
      "Crime",
      "Drama",
      "Mystery",
      "Comicbook"
    ],
    "director": [
      "Matt Reeves"
    ]
  },
  {
    "type": "movie",
    "title": "The Adam Project",
    "release_year": 2022,
    "date": "2022-03-18T00:00:00.000Z",
    "review": {
      "rating": 3
    },
    "genres": [
      "Action",
      "Adventure",
      "Comedy",
      "Sci-Fi"
    ],
    "director": [
      "Shawn Levy"
    ]
  },
  {
    "type": "movie",
    "title": "Trollhunter",
    "release_year": 2010,
    "date": "2022-04-13T00:00:00.000Z",
    "review": {
      "rating": 3
    },
    "genres": [
      "Drama",
      "Fantasy",
      "Horror",
      "Sci-Fi",
      "Thriller"
    ],
    "director": [
      "André Øvredal"
    ]
  },
  {
    "type": "movie",
    "title": "The Northman",
    "release_year": 2022,
    "date": "2022-04-15T00:00:00.000Z",
    "review": {
      "rating": 4
    },
    "genres": [
      "Action",
      "Adventure",
      "Drama",
      "Fantasy",
      "History",
      "Thriller"
    ],
    "director": [
      "Robert Eggers"
    ]
  },
  {
    "type": "movie",
    "title": "Doctor Strange in the Multiverse of Madness",
    "release_year": 2022,
    "date": "2022-05-04T00:00:00.000Z",
    "review": {
      "rating": 4
    },
    "genres": [
      "Action",
      "Adventure",
      "Fantasy",
      "Sci-Fi",
      "Horror",
      "Comicbook"
    ],
    "director": [
      "Sam Raimi"
    ]
  },
  {
    "type": "movie",
    "title": "Chip 'n Dale: Rescue Rangers",
    "release_year": 2022,
    "date": "2022-05-21T00:00:00.000Z",
    "review": {
      "rating": 3
    },
    "genres": [
      "Animation",
      "Adventure",
      "Comedy",
      "Family",
      "Mystery"
    ],
    "director": [
      "Akiva Schaffer"
    ]
  },
  {
    "type": "movie",
    "title": "Everything Everywhere All At Once",
    "release_year": 2022,
    "date": "2022-05-25T00:00:00.000Z",
    "review": {
      "rating": 4
    },
    "genres": [
      "Action",
      "Adventure",
      "Comedy",
      "Fantasy",
      "Sci-Fi"
    ],
    "director": [
      "Dan Kwan",
      "Daniel Scheinert"
    ]
  },
  {
    "type": "movie",
    "title": "Pleasure",
    "release_year": 2021,
    "date": "2022-06-16T00:00:00.000Z",
    "review": {
      "rating": 4
    },
    "genres": [
      "Drama"
    ],
    "director": [
      "Ninja Thyberg"
    ]
  },
  {
    "type": "movie",
    "title": "Thor: Love and Thunder",
    "release_year": 2022,
    "date": "2022-07-07T00:00:00.000Z",
    "review": {
      "rating": 3
    },
    "genres": [
      "Action",
      "Adventure",
      "Comedy",
      "Comicbook"
    ],
    "director": [
      "Taika Watiti"
    ]
  },
  {
    "type": "movie",
    "title": "American History X",
    "release_year": 1998,
    "date": "2022-07-23T00:00:00.000Z",
    "review": {
      "rating": 5
    },
    "genres": [
      "Crime",
      "Drama"
    ],
    "director": [
      "Tony Kaye"
    ]
  },
  {
    "type": "movie",
    "title": "The Witches (2020)",
    "release_year": 2020,
    "date": "2022-07-25T00:00:00.000Z",
    "review": {
      "rating": 3
    },
    "genres": [
      "Adventure",
      "Comedy",
      "Family",
      "Fantasy",
      "Horror",
      "Mystery"
    ],
    "director": [
      "Robert Zemeckis"
    ]
  },
  {
    "type": "movie",
    "title": "Jumper",
    "release_year": 2008,
    "date": "2022-07-31T00:00:00.000Z",
    "review": {
      "rating": 3
    },
    "genres": [
      "Action",
      "Adventure",
      "Sci-Fi"
    ],
    "director": [
      "Doug Liman"
    ]
  },
  {
    "type": "movie",
    "title": "The Last Duel",
    "release_year": 2021,
    "date": "2022-08-13T00:00:00.000Z",
    "review": {
      "rating": 4
    },
    "genres": [
      "Action",
      "Drama",
      "History"
    ],
    "director": [
      "Ridley Scott"
    ]
  },
  {
    "type": "movie",
    "title": "C'mon C'mon",
    "release_year": 2021,
    "date": "2022-08-13T00:00:00.000Z",
    "review": {
      "rating": 4
    },
    "genres": [
      "Drama"
    ],
    "director": [
      "Mike Mills"
    ]
  },
  {
    "type": "movie",
    "title": "Ghostbusters: Afterlife",
    "release_year": 2021,
    "date": "2022-08-20T00:00:00.000Z",
    "review": {
      "rating": 3
    },
    "genres": [
      "Adventure",
      "Comedy",
      "Fantasy"
    ],
    "director": [
      "Jason Reitman"
    ]
  },
  {
    "type": "movie",
    "title": "Bullet Train",
    "release_year": 2022,
    "date": "2022-08-23T00:00:00.000Z",
    "review": {
      "rating": 5
    },
    "genres": [
      "Action",
      "Comedy",
      "Thriller"
    ],
    "director": [
      "David Leitch"
    ]
  },
  {
    "type": "movie",
    "title": "Bodies Bodies Bodies",
    "release_year": 2022,
    "date": "2022-09-24T00:00:00.000Z",
    "review": {
      "rating": 3
    },
    "genres": [
      "Horror",
      "Comedy",
      "Thriller"
    ],
    "director": [
      "Halina Reijn"
    ]
  },
  {
    "type": "movie",
    "title": "Nope",
    "release_year": 2022,
    "date": "2022-09-25T00:00:00.000Z",
    "review": {
      "rating": 4
    },
    "genres": [
      "Horror",
      "Mystery",
      "Sci-Fi"
    ],
    "director": [
      "Jordan Peele"
    ]
  },
  {
    "type": "movie",
    "title": "Werewolf by Night",
    "release_year": 2022,
    "date": "2022-10-08T00:00:00.000Z",
    "review": {
      "rating": 4
    },
    "genres": [
      "Action",
      "Adventure",
      "Comedy"
    ],
    "director": [
      "Michael Giacchino"
    ]
  },
  {
    "type": "movie",
    "title": "The Naked Gun: From the Files of Police Squad!",
    "release_year": 1988,
    "date": "2022-10-22T00:00:00.000Z",
    "review": {
      "rating": 4
    },
    "genres": [
      "Comedy",
      "Crime"
    ],
    "director": [
      "David Zucker"
    ]
  },
  {
    "type": "movie",
    "title": "Barbarian",
    "release_year": 2022,
    "date": "2022-11-04T00:00:00.000Z",
    "review": {
      "rating": 4
    },
    "genres": [
      "Horror",
      "Thriller"
    ],
    "director": [
      "Zach Cregger"
    ]
  },
  {
    "type": "movie",
    "title": "Black Panther: Wakanda Forever",
    "release_year": 2022,
    "date": "2022-11-09T00:00:00.000Z",
    "review": {
      "rating": 3
    },
    "genres": [
      "Action",
      "Adventure",
      "Drama"
    ],
    "director": [
      "Ryan Coggler"
    ]
  },
  {
    "type": "movie",
    "title": "Krigsseileren",
    "release_year": 2022,
    "date": "2022-11-19T00:00:00.000Z",
    "review": {
      "rating": 5
    },
    "genres": [
      "Drama",
      "War"
    ],
    "director": [
      "Gunnar Vikene"
    ]
  },
  {
    "type": "movie",
    "title": "The Guardians of the Galaxy Holiday Special",
    "release_year": 2022,
    "date": "2022-11-25T00:00:00.000Z",
    "review": {
      "rating": 4
    },
    "genres": [
      "Action",
      "Adventure",
      "Comedy",
      "Fantasy",
      "Sci-Fi",
      "Comicbook"
    ],
    "director": [
      "James Gunn"
    ]
  },
  {
    "type": "movie",
    "title": "Glass Onion: A Knives Out Mystery",
    "release_year": 2022,
    "date": "2022-12-25T00:00:00.000Z",
    "review": {
      "rating": 3
    },
    "genres": [
      "Comedy",
      "Crime",
      "Drama"
    ],
    "director": [
      "Rian Johnson"
    ]
  },
  {
    "type": "movie",
    "title": "Verdens verste menneske",
    "release_year": 2021,
    "date": "2022-12-30T00:00:00.000Z",
    "review": {
      "rating": 4
    },
    "genres": [
      "Comedy",
      "Drama",
      "Romance"
    ],
    "director": [
      "Joachim Trier"
    ]
  },
  {
    "type": "movie",
    "title": "Avatar: The Way of Water",
    "release_year": 2022,
    "date": "2023-01-01T00:00:00.000Z",
    "review": {
      "rating": 3
    },
    "genres": [
      "Action",
      "Adventure",
      "Fantasy"
    ],
    "director": [
      "James Cameron"
    ]
  },
  {
    "type": "movie",
    "title": "Marriage Story",
    "release_year": 2019,
    "date": "2023-01-13T00:00:00.000Z",
    "review": {
      "rating": 3
    },
    "genres": [
      "Drama",
      "Romance"
    ],
    "director": [
      "Noah Baumbach"
    ]
  },
  {
    "type": "movie",
    "title": "I Don't Feel at Home in This World Anymore",
    "release_year": 2017,
    "date": "2023-01-14T00:00:00.000Z",
    "review": {
      "rating": 3
    },
    "genres": [
      "Comedy",
      "Crime",
      "Drama"
    ],
    "director": [
      "Macon Blair"
    ]
  },
  {
    "type": "movie",
    "title": "Collateral",
    "release_year": 2004,
    "date": "2023-01-21T00:00:00.000Z",
    "review": {
      "rating": 3
    },
    "genres": [
      "Action",
      "Crime",
      "Drama"
    ],
    "director": [
      "Michael Mann"
    ]
  },
  {
    "type": "movie",
    "title": "The Lighthouse",
    "release_year": 2019,
    "date": "2023-02-03T00:00:00.000Z",
    "review": {
      "rating": 3
    },
    "genres": [
      "Comedy",
      "Drama",
      "Fantasy"
    ],
    "director": [
      "Robert Eggers"
    ]
  },
  {
    "type": "movie",
    "title": "Gattaca",
    "release_year": 1997,
    "date": "2023-02-05T00:00:00.000Z",
    "review": {
      "rating": 4
    },
    "genres": [
      "Drama",
      "Sci-Fi",
      "Thriller"
    ],
    "director": [
      "Andrew Niccol"
    ]
  },
  {
    "type": "movie",
    "title": "Ant-Man and the Wasp: Quantumania",
    "release_year": 2023,
    "date": "2023-02-16T00:00:00.000Z",
    "review": {
      "rating": 3
    },
    "genres": [
      "Action",
      "Adventure",
      "Comedy"
    ],
    "director": [
      "Peyton Reed"
    ]
  },
  {
    "type": "movie",
    "title": "The Whale",
    "release_year": 2022,
    "date": "2023-02-23T00:00:00.000Z",
    "review": {
      "rating": 5
    },
    "genres": [
      "Drama"
    ],
    "director": [
      "Darren Aronofsky"
    ]
  },
  {
    "type": "movie",
    "title": "Weird: The Al Yankovic Story",
    "release_year": 2022,
    "date": "2023-02-25T00:00:00.000Z",
    "review": {
      "rating": 3
    },
    "genres": [
      "Biography",
      "Comedy",
      "Music"
    ],
    "director": [
      "Eric Appel"
    ]
  },
  {
    "type": "movie",
    "title": "Aftersun",
    "release_year": 2022,
    "date": "2023-03-04T00:00:00.000Z",
    "review": {
      "rating": 4
    },
    "genres": [
      "Drama"
    ],
    "director": [
      "Charlotte Wells"
    ]
  },
  {
    "type": "movie",
    "title": "John Wick: Chapter 4",
    "release_year": 2023,
    "date": "2023-04-04T00:00:00.000Z",
    "review": {
      "rating": 3
    },
    "genres": [
      "Action",
      "Crime",
      "Thriller"
    ],
    "director": [
      "Chad Stahelski"
    ]
  },
  {
    "type": "movie",
    "title": "Murder Mystery",
    "release_year": 2019,
    "date": "2023-04-07T00:00:00.000Z",
    "review": {
      "rating": 2
    },
    "genres": [
      "Action",
      "Comedy",
      "Crime"
    ],
    "director": [
      "Kyle Newacheck"
    ]
  },
  {
    "type": "movie",
    "title": "Murder Mystery 2",
    "release_year": 2023,
    "date": "2023-04-10T00:00:00.000Z",
    "review": {
      "rating": 2
    },
    "genres": [
      "Action",
      "Comedy",
      "Crime"
    ],
    "director": [
      "Jeremy Garelick"
    ]
  },
  {
    "type": "movie",
    "title": "The Super Mario Bros. Movie",
    "release_year": 2023,
    "date": "2023-04-15T00:00:00.000Z",
    "review": {
      "rating": 3
    },
    "genres": [
      "Animation",
      "Adventure",
      "Comedy"
    ],
    "director": [
      "Aaron Horvath",
      "Michael Jelenic",
      "Pierre Leduc"
    ]
  },
  {
    "type": "movie",
    "title": "Guardians of the Galaxy Vol. 3",
    "release_year": 2023,
    "date": "2023-05-03T00:00:00.000Z",
    "review": {
      "rating": 4
    },
    "genres": [
      "Action",
      "Adventure",
      "Comedy"
    ],
    "director": [
      "James Gunn"
    ]
  },
  {
    "type": "movie",
    "title": "Sisu",
    "release_year": 2022,
    "date": "2023-05-19T00:00:00.000Z",
    "review": {
      "rating": 4
    },
    "genres": [
      "Action",
      "War"
    ],
    "director": [
      "Jalmari Helander"
    ]
  },
  {
    "type": "movie",
    "title": "The Quiet Girl",
    "release_year": 2022,
    "date": "2023-05-27T00:00:00.000Z",
    "review": {
      "rating": 4
    },
    "genres": [
      "Drama"
    ],
    "director": [
      "Colm Bairéad"
    ]
  },
  {
    "type": "movie",
    "title": "Spider-Man: Across the Spider-Verse",
    "release_year": 2023,
    "date": "2023-06-02T00:00:00.000Z",
    "review": {
      "rating": 5
    },
    "genres": [
      "Animation",
      "Action",
      "Adventure"
    ],
    "director": [
      "Joaquim Dos Santos",
      "Kemp Powers",
      "Justin K. Thompson"
    ]
  },
  {
    "type": "movie",
    "title": "Extraction 2",
    "release_year": 2023,
    "date": "2023-06-17T00:00:00.000Z",
    "review": {
      "rating": 3
    },
    "genres": [
      "Action",
      "Thriller"
    ],
    "director": [
      "Sam Hargrave"
    ]
  },
  {
    "type": "movie",
    "title": "Luck",
    "release_year": 2022,
    "date": "2023-07-01T00:00:00.000Z",
    "review": {
      "rating": 4
    },
    "genres": [
      "Animation",
      "Adventure",
      "Comedy"
    ],
    "director": [
      "Peggy Holmes",
      "Javier Abad"
    ]
  },
  {
    "type": "movie",
    "title": "Oppenheimer",
    "release_year": 2023,
    "date": "2023-07-23T00:00:00.000Z",
    "review": {
      "rating": 5
    },
    "genres": [
      "Biography",
      "Drama",
      "History"
    ],
    "director": [
      "Christopher Nolan"
    ]
  },
  {
    "type": "movie",
    "title": "Tommy Boy",
    "release_year": 1995,
    "date": "2023-07-28T00:00:00.000Z",
    "review": {
      "rating": 3
    },
    "genres": [
      "Adventure",
      "Comedy"
    ],
    "director": [
      "Peter Segal"
    ]
  },
  {
    "type": "movie",
    "title": "Barbie",
    "release_year": 2023,
    "date": "2023-07-30T00:00:00.000Z",
    "review": {
      "rating": 4
    },
    "genres": [
      "Adventure",
      "Comedy",
      "Fantasy"
    ],
    "director": [
      "Greta Gerwig"
    ]
  },
  {
    "type": "movie",
    "title": "Kopps",
    "release_year": 2003,
    "date": "2023-08-11T00:00:00.000Z",
    "review": {
      "rating": 4
    },
    "genres": [
      "Action",
      "Comedy"
    ],
    "director": [
      "Josef Fares"
    ]
  },
  {
    "type": "movie",
    "title": "Tetris",
    "date": "2023-08-12T00:00:00.000Z",
    "genres": [
      "Biography",
      "Drama",
      "History"
    ],
    "release_year": 2023,
    "review": {
      "rating": 4
    },
    "director": [
      "Jon S. Baird"
    ]
  },
  {
    "type": "movie",
    "title": "Jalla! Jalla!",
    "date": "2023-08-22T00:00:00.000Z",
    "genres": [
      "Comedy",
      "Drama",
      "Romance"
    ],
    "release_year": 2000,
    "review": {
      "rating": 3
    },
    "director": [
      "Josef Fares"
    ]
  },
  {
    "type": "movie",
    "title": "Thomas mot Thomas",
    "date": "2023-10-07T00:00:00.000Z",
    "genres": [
      "Comedy",
      "Drama"
    ],
    "release_year": 2022,
    "review": {
      "rating": 3
    },
    "director": [
      "Jakob Rørvik"
    ]
  },
  {
    "type": "movie",
    "title": "Promising Young Woman",
    "date": "2023-10-14T00:00:00.000Z",
    "genres": [
      "Crime",
      "Drama",
      "Mystery"
    ],
    "release_year": 2020,
    "review": {
      "rating": 5
    },
    "director": [
      "Emerald Fennell"
    ]
  },
  {
    "type": "movie",
    "title": "The Marvels",
    "date": "2023-11-08T00:00:00.000Z",
    "genres": [
      "Action",
      "Adventure",
      "Fantasy"
    ],
    "release_year": 2023,
    "review": {
      "rating": 3
    },
    "director": [
      "Nia DaCosta"
    ]
  },
  {
    "type": "movie",
    "title": "The Killer",
    "date": "2023-11-11T00:00:00.000Z",
    "genres": [
      "Action",
      "Adventure",
      "Crime"
    ],
    "release_year": 2023,
    "review": {
      "rating": 4
    },
    "director": [
      "David Fincher"
    ]
  }
]